notigram/__init__.py
notigram/__main__.py
notigram-2.2.3.dist-info/licenses/LICENSE
notigram-2.2.3.dist-info/METADATA
notigram-2.2.3.dist-info/WHEEL
notigram-2.2.3.dist-info/top_level.txt
notigram-2.2.3.dist-info/RECORD
