Metadata-Version: 2.4
Name: notigram
Version: 2.2.3
Summary: A dev tool to enhance productivity
Author-email: Marina Rodriguez <mrodriguezs0218@gmail.com>
License-Expression: MIT
Project-URL: Homepage, https://github.com/Rinngell-Rezs/notigram-CLI
Project-URL: Issues, https://github.com/Rinngell-Rezs/notigram-CLI/issues
Classifier: Programming Language :: Python :: 3
Classifier: Operating System :: OS Independent
Requires-Python: >=3.7
License-File: LICENSE
Dynamic: license-file
